{
  "name": "ccc",
  "data": {
    "name": "ccc",
    "enemyTypes": [
      {
        "name": "ddd",
        "enemy": {
          "hp": 100,
          "size": 30,
          "collisionSize": 12,
          "emitters": [
            {
              "id": 0,
              "x": 0,
              "y": 0,
              "autoCycles": [],
              "cycleCounters": {
                "onShoot": {},
                "onShotgun": {},
                "onStream": {}
              },
              "start": {
                "emitter": {
                  "ammo": 100,
                  "reload": 0,
                  "direction": 0,
                  "shootRate": 5,
                  "shotgun": 1,
                  "arrays": 3,
                  "arraySpread": 360,
                  "streams": 5,
                  "streamSpread": 45,
                  "radius": 0,
                  "aimPlayer": false
                },
                "bullet": {
                  "speed": 2.5,
                  "color": "#ffffff",
                  "alpha": 1,
                  "size": 2,
                  "scaleY": 1,
                  "spin": 0,
                  "homing": 0,
                  "shape": "circle"
                }
              },
              "current": {
                "emitter": {
                  "ammo": 100,
                  "reload": 0,
                  "direction": 0,
                  "shootRate": 5,
                  "shotgun": 1,
                  "arrays": 3,
                  "arraySpread": 360,
                  "streams": 5,
                  "streamSpread": 45,
                  "radius": 0,
                  "aimPlayer": false,
                  "shootCooldownTimer": 1,
                  "currentAmmo": 100,
                  "reloadTimer": 0
                },
                "bullet": {
                  "speed": 2.5,
                  "color": "#ffffff",
                  "alpha": 1,
                  "size": 2,
                  "scaleY": 1,
                  "spin": 0,
                  "homing": 0,
                  "shape": "circle"
                }
              }
            }
          ]
        },
        "timestamp": "2025-11-18T18:31:58.200Z"
      }
    ],
    "waves": [
      {
        "spawners": [
          0
        ]
      }
    ],
    "enemySpawners": [
      {
        "id": 0,
        "x": 83,
        "y": 230,
        "startX": 83,
        "startY": 230,
        "enemiesCount": 10,
        "spawnCooldown": 60,
        "spawnDelay": 0,
        "spawnDirection": 0,
        "speed": 1,
        "dirAdd": 0,
        "xPlus": 0,
        "yPlus": 0,
        "acceleration": 0,
        "formation": true,
        "formationPoints": [
          {
            "x": -56.24324324324327,
            "y": -57.18054054054049
          },
          {
            "x": -28.09652509652512,
            "y": -78.34918918918915
          },
          {
            "x": 6.652509652509636,
            "y": -82.5135135135135
          },
          {
            "x": 29.93436293436291,
            "y": -78.6962162162162
          },
          {
            "x": 55.30115830115828,
            "y": -75.91999999999997
          },
          {
            "x": -7.594594594594625,
            "y": -62.38594594594592
          },
          {
            "x": 21.594594594594582,
            "y": -60.650810810810796
          },
          {
            "x": 40.359073359073335,
            "y": -91.8832432432432
          },
          {
            "x": -24.274131274131292,
            "y": -105.07027027027023
          },
          {
            "x": -52.07335907335909,
            "y": -99.86486486486486
          }
        ],
        "enabled": false,
        "cooldownCurrent": 45,
        "directionCurrent": 0,
        "enemyType": "ddd",
        "currentFormationPointIndex": 0,
        "spawnedCount": 2
      }
    ],
    "timestamp": "2025-11-18T18:33:03.048Z"
  },
  "uploadedBy": "user-1763185384817",
  "uploadedAt": "2025-11-18T18:33:03.054Z"
}